{
  "text": {
    "__TYPE__": "FieldContent",
    "value": "courage",
    "type": "Text"
  },
  "slices": {
    "__TYPE__": "SliceContentType",
    "value": [
      {
        "key": "question$64a1829c-f60d-4245-9dc4-ea420cf8a143",
        "name": "question",
        "widget": {
          "__TYPE__": "SharedSliceContent",
          "variation": "default",
          "primary": {
            "title": {
              "__TYPE__": "StructuredTextContent",
              "value": [
                {
                  "type": "heading1",
                  "content": {
                    "text": "Review"
                  }
                }
              ]
            },
            "description": {
              "__TYPE__": "StructuredTextContent",
              "value": [
                {
                  "type": "paragraph",
                  "content": {
                    "text": "Labore enim ex duis tempor aliqua officia nostrud tempor non ut laborum labore pariatur irure."
                  }
                }
              ]
            }
          },
          "items": [
            {
              "__TYPE__": "GroupItemContent",
              "value": []
            }
          ]
        }
      }
    ]
  }
}
